trajgenpy/Generator.py
trajgenpy/Geometries.py
trajgenpy/Logging.py
trajgenpy/Query.py
trajgenpy/Utils.py
trajgenpy/__init__.py
trajgenpy/bindings.cpython-310-x86_64-linux-gnu.so
trajgenpy-0.1.3.dist-info/METADATA
trajgenpy-0.1.3.dist-info/WHEEL
trajgenpy-0.1.3.dist-info/entry_points.txt
trajgenpy-0.1.3.dist-info/licenses/LICENSE
trajgenpy-0.1.3.dist-info/RECORD
