Metadata-Version: 2.1
Name: trajgenpy
Version: 0.1.3
Summary: TrajGenPy is a Python library that provides functionality for trajectory task generation using the Boustrophedon Cell Decomposition algorithm for coverage generation.
Author-Email: My Name <me@email.com>
Classifier: Development Status :: 4 - Beta
Classifier: License :: OSI Approved :: MIT License
Classifier: Programming Language :: Python :: 3.10
Classifier: Programming Language :: Python :: 3.11
Requires-Python: >=3.7
Provides-Extra: test
Requires-Dist: pytest; extra == "test"
